{

	"activityList":[
		{
			"id"          : 1,
			"name"        :  " versity ",
			"date"		  :  "Mon Mar 14 2016 19:33:40 GMT+0600 (Bangladesh Standard Time)",
			"description" :  "onk kaj korte hoibo versity te jaia",
			"priority"    :  "normal"
		},
		{
			"id"          : 2,
			"name"        :  " resturant ",
			"date"		  :  "Mon Mar 14 2016 19:33:40 GMT+0600 (Bangladesh Standard Time)",
			"description" :  "add dite hoibo friends er loge",
			"priority"    :  "normal"
		},
		{
			"id"          : 3,
			"name"        :  " coding ",
			"date"		  :  "Mon Mar 14 2016 19:33:40 GMT+0600 (Bangladesh Standard Time)",
			"description" :  "have to build a great application",
			"priority"    :  "high"
		}
		,
		{
			"id"          : 4,
			"name"        :  " shopping ",
			"date"		  :  "Mon Mar 14 2016 19:33:40 GMT+0600 (Bangladesh Standard Time)",
			"description" :  "have to buy a lot of stuff for my pc",
			"priority"    :  "high"
		}
 	]

}